Workbook

Sheet Read Me
B2: SDE-2 Interview Prep Tracker
B4: Goal | C4: Clear the MAJORITY of SDE-2 interviews. Strategy = breadth of PATTERNS + solid fundamentals, NOT grinding the hardest Hard problems. Tier 3 items are 'do if time permits'.
B5: How to use | C5: Work the 'NeetCode 150' tab by Tier. Update Status (dropdown) + Confidence (1-5) as you go. The Dashboard tab auto-summarizes your progress.
B6: Tiering | C6: Tier 1 = core, high-frequency, MUST be automatic. Tier 2 = important, know the pattern cold. Tier 3 = harder / lower-frequency, attempt after Tiers 1-2.
B7: Suggested order | C7: Patterns first (recognize the shape) -> Tier 1 across all categories -> Tier 2 -> revisit weak ones -> Tier 3. Then layer in System Design + Fundamentals.
B8: Tabs | C8: NeetCode 150 (143-ish problems) | DSA Patterns | System Design | SD Scenarios | CS Fundamentals | LLD & OOD | Behavioral | Resources | Dashboard
B9: Time budget | C9: Tier 1 problem: aim < 20 min. If stuck > 30 min, read the solution, understand it, mark 'Needs Review', and re-attempt in 3-5 days (spaced repetition).
B10: Confidence scale | C10: 1 = no idea | 2 = needed solution | 3 = solved w/ hints | 4 = solved cleanly | 5 = can teach it. Only 4-5 counts as 'done' for interviews.
B11: SDE-2 extras | C11: Beyond DSA: System Design, Low-Level Design / OOD, CS Fundamentals, and Behavioral (ownership + influence) are all evaluated. Don't skip them.
B12: Free first | C12: Every resource link is free unless marked 'Paid'/'Freemium' in the Resources tab. NeetCode + System Design Primer + Hello Interview cover ~80% of needs for free.
B14: Legend
B15: Tier 1 | C15: Core / high-frequency — master these
B16: Tier 2 | C16: Important — know the pattern
B17: Tier 3 | C17: Harder / lower-frequency — do if time permits

Sheet NeetCode 150
A1: NeetCode 150 — tiered for SDE-2 (focus Tier 1 & 2)
A2: # | B2: Category | C2: Problem | D2: Difficulty | E2: Tier | F2: Pattern / Technique | G2: LeetCode Link | H2: Status | I2: Confidence (1-5) | J2: Attempts | K2: Last Done | L2: Notes
A3: 1 | B3: Arrays & Hashing | C3: Contains Duplicate | D3: Easy | E3: 1 | F3: Hash set | G3: Solve | H3: Not Started
A4: 2 | B4: Arrays & Hashing | C4: Valid Anagram | D4: Easy | E4: 1 | F4: Hash map / count | G4: Solve | H4: Not Started
A5: 3 | B5: Arrays & Hashing | C5: Two Sum | D5: Easy | E5: 1 | F5: Hash map complement | G5: Solve | H5: Not Started
A6: 4 | B6: Arrays & Hashing | C6: Group Anagrams | D6: Medium | E6: 1 | F6: Hash map keyed by signature | G6: Solve | H6: Not Started
A7: 5 | B7: Arrays & Hashing | C7: Top K Frequent Elements | D7: Medium | E7: 1 | F7: Bucket sort / heap | G7: Solve | H7: Not Started
A8: 6 | B8: Arrays & Hashing | C8: Encode and Decode Strings | D8: Medium | E8: 2 | F8: Length-prefix encoding | G8: Solve | H8: Not Started
A9: 7 | B9: Arrays & Hashing | C9: Product of Array Except Self | D9: Medium | E9: 1 | F9: Prefix/suffix products | G9: Solve | H9: Not Started
A10: 8 | B10: Arrays & Hashing | C10: Valid Sudoku | D10: Medium | E10: 2 | F10: Hash sets per row/col/box | G10: Solve | H10: Not Started
A11: 9 | B11: Arrays & Hashing | C11: Longest Consecutive Sequence | D11: Medium | E11: 1 | F11: Hash set sequence walk | G11: Solve | H11: Not Started
A12: 10 | B12: Two Pointers | C12: Valid Palindrome | D12: Easy | E12: 1 | F12: Two pointers | G12: Solve | H12: Not Started
A13: 11 | B13: Two Pointers | C13: Two Sum II Input Array Is Sorted | D13: Medium | E13: 1 | F13: Two pointers sorted | G13: Solve | H13: Not Started
A14: 12 | B14: Two Pointers | C14: 3Sum | D14: Medium | E14: 1 | F14: Sort + two pointers | G14: Solve | H14: Not Started
... A152: 150 | B152: Bit Manipulation | C152: Reverse Integer | D152: Medium | E152: 2 | F152: Overflow handling | G152: Solve | H152: Not Started

Sheet DSA Patterns
A1: DSA Patterns — learn to RECOGNIZE the shape of a problem
A2: Pattern | B2: Recognize when… | C2: Key idea | D2: Example problems
A3: Two Pointers | B3: Sorted array, pair/triplet sums, palindrome checks | C3: Move L/R inward based on a condition; O(n) instead of O(n^2) | D3: Two Sum II, 3Sum, Container With Most Water
A4: Sliding Window | B4: Contiguous subarray/substring with a constraint (longest/shortest/k) | C4: Expand right, shrink left when constraint violated | D4: Longest Substring w/o Repeat, Min Window Substring
A5: Fast & Slow Pointers | B5: Cycle detection, find middle, nth-from-end in linked list | C5: Two pointers at different speeds | D5: Linked List Cycle, Find Duplicate, Reorder List
A6: Hash Map / Set | B6: Need O(1) lookup, counting, complement, dedup | C6: Trade space for time | D6: Two Sum, Group Anagrams, Longest Consecutive
A7: Monotonic Stack | B7: Next greater/smaller element, histogram, spans | C7: Maintain increasing/decreasing stack | D7: Daily Temperatures, Largest Rectangle
A8: Binary Search | B8: Sorted input OR monotonic answer space (min/max feasible value) | C8: Halve search space each step; 'BS on answer' | D8: Koko Bananas, Search Rotated, Median Two Arrays
A9: BFS | B9: Shortest path in unweighted graph/grid, level-order | C9: Queue, process layer by layer | D9: Rotting Oranges, Word Ladder, Level Order
A10: DFS / Backtracking | B10: Explore all paths, combinations, permutations, subsets | C10: Recurse, choose, explore, un-choose | D10: Subsets, Combination Sum, Word Search, N-Queens
A11: Topological Sort | B11: Dependency ordering in a DAG, cycle detection in directed graph | C11: Kahn's (indegree+queue) or DFS post-order | D11: Course Schedule I/II, Alien Dictionary
A12: Union-Find (DSU) | B12: Connectivity, grouping, cycle detection in undirected graph | C12: Path compression + union by rank | D12: Connected Components, Redundant Connection
A13: Heap / Priority Queue | B13: Top-K, running median, merge-K, scheduling | C13: Min/max heap for partial ordering | D13: Top K Frequent, Merge K Lists, Find Median Stream
... A19: Bit Manipulation | B19: XOR tricks, single element, subset enumeration | C19: XOR cancels pairs; bitmask for subsets | D19: Single Number, Counting Bits, Subsets via bitmask

Sheet System Design
A1: System Design — core building blocks for SDE-2
A2: Topic | B2: What to know | C2: Free Resource | D2: Link | E2: Status | F2: Notes
A3: Interview framework | B3: Requirements -> estimates -> API -> high-level design -> deep dive -> bottlenecks. Drive the conversation. | C3: Hello Interview: SD in a Hurry | D3: Open | E3: Not Started
A4: Back-of-envelope estimation | B4: QPS, storage, bandwidth, memory; powers of 2, latency numbers every dev should know | C4: System Design Primer (Appendix) | D4: Open | E4: Not Started
A5: Scaling fundamentals | B5: Vertical vs horizontal scaling, stateless services, scaling reads vs writes | C5: System Design Primer | D5: Open | E5: Not Started
A6: Load balancing | B6: L4 vs L7, algorithms (round robin, least conn, consistent hashing), health checks | C6: System Design Primer: LB | D6: Open | E6: Not Started
A7: Caching | B7: Cache-aside/write-through/write-back, eviction (LRU/LFU), TTL, Redis/Memcached, thundering herd | C7: System Design Primer: Cache | D7: Open | E7: Not Started
A8: Databases: SQL vs NoSQL | B8: When to pick relational vs document/KV/wide-column/graph; access patterns drive choice | C8: System Design Primer: DB | D8: Open | E8: Not Started
A9: Replication & partitioning | B9: Leader-follower, multi-leader, sharding strategies, consistent hashing, hot partitions | C9: DDIA (book) ch.5-6 / ByteByteGo | D9: Open | E9: Not Started
A10: CAP & consistency models | B10: CAP/PACELC, strong vs eventual consistency, quorum (R+W>N) | C10: System Design Primer: CAP | D10: Open | E10: Not Started
A11: Message queues & streaming | B11: Kafka/RabbitMQ, pub-sub, at-least/at-most/exactly-once, backpressure, decoupling | C11: ByteByteGo / Kafka docs | D11: Open | E11: Not Started
A12: Indexing | B12: B-tree vs LSM-tree, composite indexes, when indexes hurt writes | C12: DDIA ch.3 / Use The Index, Luke | D12: Open | E12: Not Started
A13: Rate limiting | B13: Token bucket, leaky bucket, fixed/sliding window; distributed rate limiting | C13: Hello Interview / ByteByteGo | D13: Open | E13: Not Started
A14: CDN & content delivery | B14: Edge caching, push vs pull, static asset offload | C14: System Design Primer: CDN | D14: Open | E14: Not Started
... A19: Concurrency at scale | B19: Locks vs lock-free, optimistic concurrency, distributed locks (Redlock caveats) | C19: Martin Kleppmann Redlock post | D19: Open | E19: Not Started

Sheet SD Scenarios
A1: System Design — practice scenarios (do Tier 1 & 2 first)
A2: Scenario | B2: Tier | C2: Topics it tests | D2: Status | E2: Notes
A3: Design a URL shortener (TinyURL) | B3: 1 | C3: ID generation, KV store, caching, redirect, base62 | D3: Not Started
A4: Design a rate limiter | B4: 1 | C4: Token bucket, distributed counters, Redis | D4: Not Started
A5: Design a key-value store / cache | B5: 1 | C5: Consistent hashing, replication, eviction | D5: Not Started
A6: Design a notification / messaging system | B6: 1 | C6: Queues, fan-out, push vs pull, delivery guarantees | D6: Not Started
A7: Design a news feed (Twitter/Instagram) | B7: 2 | C7: Fan-out on write vs read, feed ranking, caching | D7: Not Started
A8: Design a chat system (WhatsApp/Slack) | B8: 2 | C8: WebSockets, presence, message ordering, storage | D8: Not Started
A9: Design a web crawler | B9: 2 | C9: BFS frontier, dedup, politeness, distributed workers | D9: Not Started
A10: Design a typeahead / autocomplete | B10: 2 | C10: Trie, top-K, caching, prefix sharding | D10: Not Started
A11: Design a file storage / Dropbox | B11: 2 | C11: Chunking, metadata, sync, dedup | D11: Not Started
A12: Design a ride-sharing service (Uber) | B12: 2 | C12: Geospatial index (geohash/quadtree), matching, ETA | D12: Not Started
A13: Design a payment system | B13: 2 | C13: Idempotency, double-entry ledger, consistency, reconciliation | D13: Not Started
A14: Design YouTube / video streaming | B14: 3 | C14: CDN, transcoding pipeline, blob storage, adaptive bitrate | D14: Not Started
... A16: Design a ticket booking system | B16: 3 | C16: Concurrency, locking inventory, payment, overselling | D16: Not Started

Sheet CS Fundamentals
A1: CS Fundamentals — frequently probed in SDE-2 rounds
A2: Area | B2: Topic | C2: Key points | D2: Free Resource | E2: Link | F2: Status
A3: Operating Systems | B3: Process vs thread | C3: Address space, context switch cost, when to use threads vs processes | D3: OSTEP (free book) | E3: Open | F3: Not Started
A4: Operating Systems | B4: Concurrency primitives | C4: Mutex, semaphore, condition variable, deadlock (4 conditions), starvation | D4: OSTEP: Concurrency | E4: Open | F4: Not Started
A5: Operating Systems | B5: Scheduling | C5: FCFS, round robin, priority, MLFQ; preemption | D5: OSTEP: Scheduling | E5: Open | F5: Not Started
A6: Operating Systems | B6: Memory management | C6: Virtual memory, paging, TLB, page faults, segmentation | D6: OSTEP: VM | E6: Open | F6: Not Started
A7: Operating Systems | B7: Synchronization problems | C7: Producer-consumer, readers-writers, dining philosophers | D7: OSTEP | E7: Open | F7: Not Started
A8: Networking | B8: OSI / TCP-IP model | C8: Layers and what lives where; encapsulation | D8: Kurose & Ross site | E8: Open | F8: Not Started
A9: Networking | B9: TCP vs UDP | C9: Handshake, reliability, ordering, flow/congestion control; when to use each | D9: Kurose & Ross | E9: Open | F9: Not Started
A10: Networking | B10: HTTP/HTTPS | C10: Methods, status codes, HTTP/1.1 vs 2 vs 3, TLS handshake, keep-alive | D10: MDN HTTP | E10: Open | F10: Not Started
A11: Networking | B11: DNS | C11: Resolution flow, recursive vs iterative, caching, records | D11: Cloudflare Learning | E11: Open | F11: Not Started
A12: Networking | B12: What happens when you type a URL | C12: End-to-end: DNS -> TCP -> TLS -> HTTP -> render. Classic interview Q | D12: alex/what-happens GitHub | E12: Open | F12: Not Started
A13: Databases | B13: ACID & transactions | C13: Atomicity, consistency, isolation, durability; why each matters | D13: DDIA ch.7 / GfG | E13: Open | F13: Not Started
... A21: Complexity | B21: Big-O analysis | C21: Time & space, amortized analysis, common complexities, recurrence (Master theorem) | D21: Big-O Cheat Sheet | E21: Open | F21: Not Started

Sheet LLD & OOD
A1: Low-Level Design & OOD — common SDE-2 design round
A2: Topic | B2: Key points | C2: Free Resource | D2: Link | E2: Status
A3: OOP fundamentals | B3: Encapsulation, abstraction, inheritance, polymorphism; composition over inheritance | C3: Refactoring Guru | D3: Open | E3: Not Started
A4: SOLID principles | B4: SRP, OCP, LSP, ISP, DIP with concrete code examples | C4: Refactoring Guru / GfG | D4: Open | E4: Not Started
A5: Design patterns: Creational | B5: Factory, Abstract Factory, Builder, Singleton, Prototype | C5: Refactoring Guru | D5: Open | E5: Not Started
A6: Design patterns: Structural | B6: Adapter, Decorator, Facade, Proxy, Composite | C6: Refactoring Guru | D6: Open | E6: Not Started
A7: Design patterns: Behavioral | B7: Strategy, Observer, State, Command, Iterator | C7: Refactoring Guru | D7: Open | E7: Not Started
A8: LLD: Parking lot | B8: Classic OOD: classes, enums, interfaces, extensibility | C8: awesome-low-level-design | D8: Open | E8: Not Started
A9: LLD: Elevator system | B9: State machine, scheduling, concurrency | C9: awesome-low-level-design | D9: Open | E9: Not Started
A10: LLD: Library / BookMyShow | B10: Entities, relationships, concurrency on booking | C10: awesome-low-level-design | D10: Open | E10: Not Started
A11: LLD: Rate limiter / Logger / Cache (LRU) | B11: Common LLD rounds at SDE-2 level | C11: awesome-low-level-design | D11: Open | E11: Not Started
A12: UML basics | B12: Class diagrams, relationships (assoc/aggregation/composition), sequence diagrams | C12: Refactoring Guru | D12: Open | E12: Not Started

Sheet Behavioral
A1: Behavioral — SDE-2 = ownership, influence, judgment
A2: Theme | B2: What they assess | C2: Prep tip | D2: Resource | E2: Link | F2: My story (1-2 lines)
A3: STAR method | B3: Structured storytelling: Situation, Task, Action, Result | C3: Prep 8-10 stories mapped to multiple themes; quantify Results | D3: The Muse: STAR | E3: Open
A4: Ownership / impact | B4: Did you drive outcomes beyond your scope? | C4: Have a story where you owned a problem end-to-end | D4: Levels.fyi behavioral guide | E4: Open
A5: Conflict / disagreement | B5: How you handle disagreement with peers/managers | C5: Show data-driven resolution, not ego | D5: - | E5: -
A6: Failure / mistake | B6: Self-awareness and learning | C6: Pick a real failure + concrete lesson + what changed after | D6: - | E6: -
A7: Dealing with ambiguity | B7: Decision-making with incomplete info | C7: Show how you scoped, prioritized, and unblocked yourself | D7: - | E7: -
A8: Mentorship / leadership | B8: Senior signal: do you lift others? | C8: SDE-2 expects influence beyond own code | D8: - | E8: -
A9: Project deep-dive | B9: Technical depth on something you built | C9: Be ready to whiteboard YOUR system's architecture & trade-offs | D9: - | E9: -
A10: Why this company / role | B10: Motivation and fit | C10: Tie to specifics, not generic praise | D10: - | E10: -

Sheet Resources
A1: Master Resource List (free unless marked otherwise)
A2: Category | B2: Resource | C2: Type | D2: Cost | E2: Link
A3: DSA | B3: NeetCode 150 (practice + videos) | C3: Practice/Video | D3: Free | E3: Open
A4: DSA | B4: NeetCode Roadmap | C4: Roadmap | D4: Free | E4: Open
A5: DSA | B5: LeetCode | C5: Practice | D5: Free (Premium paid) | E5: Open
A6: DSA | B6: Big-O Cheat Sheet | C6: Reference | D6: Free | E6: Open
A7: DSA | B7: AlgoMonster patterns | C7: Reference | D7: Freemium | E7: Open
A8: DSA | B8: Tech Interview Handbook | C8: Guide | D8: Free | E8: Open
A9: DSA | B9: Grokking Coding Interview Patterns | C9: Course | D9: Paid | E9: Open
A10: System Design | B10: System Design Primer | C10: Repo/Guide | D10: Free | E10: Open
A11: System Design | B11: Hello Interview - System Design | C11: Guide/Video | D11: Free | E11: Open
A12: System Design | B12: ByteByteGo Blog (Alex Xu) | C12: Blog | D12: Freemium | E12: Open
A13: System Design | B13: Gaurav Sen (YouTube) | C13: Video | D13: Free | E13: Open
... A31: General | B31: Pramp / interviewing.io (mock interviews) | C31: Mock | D31: Freemium | E31: Open

Sheet Dashboard
B2: Progress Dashboard
B4: NeetCode 150 — Overall
B5: Total problems | C5: =COUNTA('NeetCode 150'!C3:C200) -> 150
B6: Solved | C6: =COUNTIF('NeetCode 150'!H3:H200,"Solved") -> 0
B7: In Progress | C7: =COUNTIF('NeetCode 150'!H3:H200,"In Progress") -> 0
B8: Needs Review | C8: =COUNTIF('NeetCode 150'!H3:H200,"Needs Review") -> 0
B9: Not Started | C9: =COUNTIF('NeetCode 150'!H3:H200,"Not Started") -> 150
B10: % Complete | C10: =IF(C5=0,0,(C6)/C5) -> 0
B11: Interview-ready (Conf 4-5) | C11: =COUNTIF('NeetCode 150'!I3:I200,">=4") -> 0
B13: By Tier — Solved / Total
B14: Tier | C14: Total | D14: Solved | E14: % Done
B15: Tier 1 | C15: =COUNTIF('NeetCode 150'!E3:E200,1) -> 84 | D15: =COUNTIFS('NeetCode 150'!E3:E200,1,'NeetCode 150'!H3:H200,"Solved") -> 0 | E15: =IF(C15=0,0,D15/C15) -> 0
B16: Tier 2 | C16: =COUNTIF('NeetCode 150'!E3:E200,2) -> 48 | D16: =COUNTIFS('NeetCode 150'!E3:E200,2,'NeetCode 150'!H3:H200,"Solved") -> 0 | E16: =IF(C16=0,0,D16/C16) -> 0
B17: Tier 3 | C17: =COUNTIF('NeetCode 150'!E3:E200,3) -> 18 | D17: =COUNTIFS('NeetCode 150'!E3:E200,3,'NeetCode 150'!H3:H200,"Solved") -> 0 | E17: =IF(C17=0,0,D17/C17) -> 0
B20: By Category — Solved / Total
B21: Category | C21: Total | D21: Solved | E21: % Done
B22: Arrays & Hashing | C22: =COUNTIF('NeetCode 150'!B3:B200,B22) -> 9 | D22: =COUNTIFS('NeetCode 150'!B3:B200,B22,'NeetCode 150'!H3:H200,"Solved") -> 0 | E22: =IF(C22=0,0,D22/C22) -> 0
B23: Two Pointers | C23: =COUNTIF('NeetCode 150'!B3:B200,B23) -> 5 | D23: =COUNTIFS('NeetCode 150'!B3:B200,B23,'NeetCode 150'!H3:H200,"Solved") -> 0 | E23: =IF(C23=0,0,D23/C23) -> 0
B24: Sliding Window | C24: =COUNTIF('NeetCode 150'!B3:B200,B24) -> 6 | D24: =COUNTIFS('NeetCode 150'!B3:B200,B24,'NeetCode 150'!H3:H200,"Solved") -> 0 | E24: =IF(C24=0,0,D24/C24) -> 0
B25: Stack | C25: =COUNTIF('NeetCode 150'!B3:B200,B25) -> 7 | D25: =COUNTIFS('NeetCode 150'!B3:B200,B25,'NeetCode 150'!H3:H200,"Solved") -> 0 | E25: =IF(C25=0,0,D25/C25) -> 0
B26: Binary Search | C26: =COUNTIF('NeetCode 150'!B3:B200,B26) -> 7 | D26: =COUNTIFS('NeetCode 150'!B3:B200,B26,'NeetCode 150'!H3:H200,"Solved") -> 0 | E26: =IF(C26=0,0,D26/C26) -> 0
B27: Linked List | C27: =COUNTIF('NeetCode 150'!B3:B200,B27) -> 11 | D27: =COUNTIFS('NeetCode 150'!B3:B200,B27,'NeetCode 150'!H3:H200,"Solved") -> 0 | E27: =IF(C27=0,0,D27/C27) -> 0
B28: Trees | C28: =COUNTIF('NeetCode 150'!B3:B200,B28) -> 15 | D28: =COUNTIFS('NeetCode 150'!B3:B200,B28,'NeetCode 150'!H3:H200,"Solved") -> 0 | E28: =IF(C28=0,0,D28/C28) -> 0
B29: Tries | C29: =COUNTIF('NeetCode 150'!B3:B200,B29) -> 3 | D29: =COUNTIFS('NeetCode 150'!B3:B200,B29,'NeetCode 150'!H3:H200,"Solved") -> 0 | E29: =IF(C29=0,0,D29/C29) -> 0
B30: Heap / Priority Queue | C30: =COUNTIF('NeetCode 150'!B3:B200,B30) -> 7 | D30: =COUNTIFS('NeetCode 150'!B3:B200,B30,'NeetCode 150'!H3:H200,"Solved") -> 0 | E30: =IF(C30=0,0,D30/C30) -> 0
B31: Backtracking | C31: =COUNTIF('NeetCode 150'!B3:B200,B31) -> 9 | D31: =COUNTIFS('NeetCode 150'!B3:B200,B31,'NeetCode 150'!H3:H200,"Solved") -> 0 | E31: =IF(C31=0,0,D31/C31) -> 0
B32: Graphs | C32: =COUNTIF('NeetCode 150'!B3:B200,B32) -> 13 | D32: =COUNTIFS('NeetCode 150'!B3:B200,B32,'NeetCode 150'!H3:H200,"Solved") -> 0 | E32: =IF(C32=0,0,D32/C32) -> 0
B33: Advanced Graphs | C33: =COUNTIF('NeetCode 150'!B3:B200,B33) -> 6 | D33: =COUNTIFS('NeetCode 150'!B3:B200,B33,'NeetCode 150'!H3:H200,"Solved") -> 0 | E33: =IF(C33=0,0,D33/C33) -> 0
B34: 1-D Dynamic Programming | C34: =COUNTIF('NeetCode 150'!B3:B200,B34) -> 12 | D34: =COUNTIFS('NeetCode 150'!B3:B200,B34,'NeetCode 150'!H3:H200,"Solved") -> 0 | E34: =IF(C34=0,0,D34/C34) -> 0
B35: 2-D Dynamic Programming | C35: =COUNTIF('NeetCode 150'!B3:B200,B35) -> 11 | D35: =COUNTIFS('NeetCode 150'!B3:B200,B35,'NeetCode 150'!H3:H200,"Solved") -> 0 | E35: =IF(C35=0,0,D35/C35) -> 0
B36: Greedy | C36: =COUNTIF('NeetCode 150'!B3:B200,B36) -> 8 | D36: =COUNTIFS('NeetCode 150'!B3:B200,B36,'NeetCode 150'!H3:H200,"Solved") -> 0 | E36: =IF(C36=0,0,D36/C36) -> 0
B37: Intervals | C37: =COUNTIF('NeetCode 150'!B3:B200,B37) -> 6 | D37: =COUNTIFS('NeetCode 150'!B3:B200,B37,'NeetCode 150'!H3:H200,"Solved") -> 0 | E37: =IF(C37=0,0,D37/C37) -> 0
B38: Math & Geometry | C38: =COUNTIF('NeetCode 150'!B3:B200,B38) -> 8 | D38: =COUNTIFS('NeetCode 150'!B3:B200,B38,'NeetCode 150'!H3:H200,"Solved") -> 0 | E38: =IF(C38=0,0,D38/C38) -> 0
B39: Bit Manipulation | C39: =COUNTIF('NeetCode 150'!B3:B200,B39) -> 7 | D39: =COUNTIFS('NeetCode 150'!B3:B200,B39,'NeetCode 150'!H3:H200,"Solved") -> 0 | E39: =IF(C39=0,0,D39/C39) -> 0
